Metadata-Version: 2.1
Name: python-1inch
Version: 0.0.2
Summary: A python wraper around the 1INCH DEX API.
Home-page: https://github.com/tudorelu/python_1inch
Author: Tudor Barbulescu
Author-email: hello@tudorbarbulescu.com
License: UNKNOWN
Project-URL: Bug Tracker, https://github.com/tudorelu/python_1inch/issues
Platform: UNKNOWN
Classifier: Programming Language :: Python :: 3
Classifier: License :: OSI Approved :: MIT License
Classifier: Operating System :: OS Independent
Requires-Python: >=3.6
